bocode/BBOB.py
bocode/DTLZ.py
bocode/MODAct.py
bocode/WFG.py
bocode/ZDT.py
bocode/__init__.py
bocode/base.py
bocode/exceptions.py
bocode/search_benchmarks.py
bocode/visualization.py
bocode/BoTorch/BaseBotorch.py
bocode/BoTorch/__init__.py
bocode/BoTorch/botorch_MultiFidelity.py
bocode/BoTorch/botorch_MultiFidelityMultiObj.py
bocode/BoTorch/botorch_MultiObj.py
bocode/BoTorch/botorch_SensitivityAnalysis.py
bocode/CEC/BaseOpfunuCEC.py
bocode/CEC/CEC2007.py
bocode/CEC/CEC2017.py
bocode/CEC/CEC2019.py
bocode/CEC/__init__.py
bocode/CEC/CEC2020_RW_Constrained/CEC2020_p1_20.py
bocode/CEC/CEC2020_RW_Constrained/CEC2020_p21_33.py
bocode/CEC/CEC2020_RW_Constrained/CEC2020_p34.py
bocode/CEC/CEC2020_RW_Constrained/CEC2020_p35.py
bocode/CEC/CEC2020_RW_Constrained/CEC2020_p36.py
bocode/CEC/CEC2020_RW_Constrained/CEC2020_p37.py
bocode/CEC/CEC2020_RW_Constrained/CEC2020_p38.py
bocode/CEC/CEC2020_RW_Constrained/CEC2020_p39.py
bocode/CEC/CEC2020_RW_Constrained/CEC2020_p40_57.py
bocode/CEC/CEC2020_RW_Constrained/__init__.py
bocode/CEC/CEC2020_RW_Constrained/helperFuncs.py
bocode/CEC/CEC2020_RW_Constrained/input_data/FunctionPS11_B.txt
bocode/CEC/CEC2020_RW_Constrained/input_data/FunctionPS11_G.txt
bocode/CEC/CEC2020_RW_Constrained/input_data/FunctionPS11_P.txt
bocode/CEC/CEC2020_RW_Constrained/input_data/FunctionPS11_Q.txt
bocode/CEC/CEC2020_RW_Constrained/input_data/FunctionPS14_linedata.txt
bocode/CEC/CEC2020_RW_Constrained/input_data/FunctionPS1_B.txt
bocode/CEC/CEC2020_RW_Constrained/input_data/FunctionPS1_G.txt
bocode/CEC/CEC2020_RW_Constrained/input_data/FunctionPS1_P.txt
bocode/CEC/CEC2020_RW_Constrained/input_data/FunctionPS1_Q.txt
bocode/CEC/CEC2020_RW_Constrained/input_data/FunctionPS2_B.txt
bocode/CEC/CEC2020_RW_Constrained/input_data/FunctionPS2_G.txt
bocode/CEC/CEC2020_RW_Constrained/input_data/FunctionPS2_P.txt
bocode/CEC/CEC2020_RW_Constrained/input_data/FunctionPS2_Q.txt
bocode/CEC/CEC2020_RW_Constrained/input_data/FunctionRM_dairy.txt
bocode-1.0.0.dist-info/licenses/LICENSE
bocode-1.0.0.dist-info/METADATA
bocode-1.0.0.dist-info/WHEEL
bocode-1.0.0.dist-info/top_level.txt
bocode-1.0.0.dist-info/RECORD
