Metadata-Version: 2.4
Name: bocode
Version: 1.0.0
Summary: BOCoDe is a Python library contains optimization benchmark problems.
Author: Rosen Yu, Advaith Narayanan, Cyril Picard, Faez Ahmed
License-Expression: MIT
Project-URL: Homepage, https://github.com/rosenyu304/BOCoDe/
Project-URL: Repository, https://github.com/rosenyu304/BOCoDe/
Keywords: engineering design,optimization,benchmark,engineering,bayesian-optimization
Classifier: Development Status :: 4 - Beta
Classifier: Programming Language :: Python :: 3
Classifier: Programming Language :: Python :: 3.10
Classifier: Programming Language :: Python :: 3.11
Classifier: Programming Language :: Python :: 3.12
Classifier: Intended Audience :: Science/Research
Requires-Python: >=3.10
License-File: LICENSE
Requires-Dist: botorch
Requires-Dist: torch
Requires-Dist: numpy
Requires-Dist: cocopp
Requires-Dist: coco-experiment
Requires-Dist: pygame
Requires-Dist: Box2D
Requires-Dist: slientruss3d
Requires-Dist: openpyxl
Requires-Dist: diversipy
Requires-Dist: optproblems
Requires-Dist: opfunu
Requires-Dist: gym
Requires-Dist: gymnasium[MuJoCo]
Requires-Dist: scipy
Requires-Dist: gpy>=1.13.0
Requires-Dist: onnxruntime>=1.22.0
Requires-Dist: modact
Requires-Dist: pandas
Provides-Extra: viz
Requires-Dist: dash; extra == "viz"
Requires-Dist: plotly; extra == "viz"
Requires-Dist: matplotlib; extra == "viz"
Dynamic: license-file
